	[{
		"id": 1,
		"jobName":"Full-Stack Developer",
		"jobDescription": "Prepares design needed for the quality testing",
		"company": "AllTail Web Solutions",
		"rating": "4.4",
		"place": "Pasong Tamo, Quezon City",
		"salary": "32,000.00",
		"datePosted": "09-12-2022",
		"vacancies":20,
		"workType":["Full-time","Part-time","Contractual"]
	},
{
	"id": 2,
	"jobName":"Network Engineer",
	"jobDescription": "Prepares design architecture and networks",
	"company": "Google DC Philippines",
	"rating": "4.5",
	"place": "Mandaluyong, Madaya City",
	"salary": "15,000.00",
	"datePosted": "09-12-2022",
	"vacancies":2,
	"workType":["Full-time","Part-time"]
},
{
	"id": 3,
	"jobName":"UI/UX Engineer",
	"jobDescription": "Prepares research for quality research.",
	"company": "Clockstop Solutions",
	"rating": "5.0",
	"place": "Lipa, Taguig City",
	"salary": "25,000.00",
	"datePosted": "09-11-2022",
	"vacancies":3,
	"workType":["Full-time","Part-time","Contractual"]
},
{
	"id": 4,
	"jobName":"Blockchain Developer",
	"jobDescription": "Prepares research for quality research.",
	"company": "Consolatrix IT Solutions",
	"rating": "5.0",
	"place": "Plaridel, ImizCity, Sorsorgon",
	"salary": "85,000.00",
	"datePosted": "09-11-2022",
	"vacancies":8,
	"workType":["Full-time","Contractual"]
},
{
	"id": 5,
	"jobName":"QA Tester Jr.",
	"jobDescription": "Prepares extensive testing on the quality of the product.",
	"company": "JumbSolutions Inc.,",
	"rating": "4.0",
	"place": "Imus, Cavite",
	"salary": "100,000.00",
	"datePosted": "09-11-2022",
	"vacancies":8,
	"workType":["Full-time","Contractual"]
}]

